{
  "alerts": [
    {
      "symbol": "VPN",
      "name": "Vaping Penguin Normie",
      "score": 50,
      "alert_type": "🆕 NEW_PAIR",
      "price": 1.726e-05,
      "price_change_5m": 10.74,
      "price_change_1h": 6.62,
      "price_change_24h": -48.33,
      "volume_24h": 172012.37,
      "liquidity": 10089.27,
      "market_cap": 17267.0,
      "pair_url": "https://dexscreener.com/solana/59FRT4Eiz2B5kVwFSwR9rHNzshMitnnNebFceuH7pump",
      "token_address": "59FRT4Eiz2B5kVwFSwR9rHNzshMitnnNebFceuH7pump",
      "chain": "solana",
      "signals": [
        "⚡ 5m rocket: +10.7%",
        "⚡ Heavy buying: 5 buys vs 1 sells (5m)",
        "🎯 Micro cap gem: $17,267",
        "🔥 Active trading: 5,434 txns (24h)"
      ],
      "timestamp": "2026-03-29T12:45:09.674466"
    },
    {
      "symbol": "TARO",
      "name": "Ryotaro",
      "score": 45,
      "alert_type": "🔔 ALERT",
      "price": 0.0004125,
      "price_change_5m": 1.86,
      "price_change_1h": 19.36,
      "price_change_24h": -28.2,
      "volume_24h": 38.59,
      "liquidity": 33.72,
      "market_cap": 412517.0,
      "pair_url": "https://dexscreener.com/solana/6MFiqqkS4MUwmkoa8sj5UJcFzJGVxHD1yEpoyRRUdoge",
      "token_address": "6MFiqqkS4MUwmkoa8sj5UJcFzJGVxHD1yEpoyRRUdoge",
      "chain": "solana",
      "signals": [
        "📈 1h surge: +19.4%",
        "⚡ Heavy buying: 1 buys vs 0 sells (5m)",
        "💪 Buy pressure: 9 buys vs 1 sells (1h)",
        "🎯 Micro cap gem: $412,517"
      ],
      "timestamp": "2026-03-29T12:45:09.674466"
    },
    {
      "symbol": "PUBES",
      "name": "pubes",
      "score": 44,
      "alert_type": "🆕 NEW_PAIR",
      "price": 2.194e-05,
      "price_change_5m": 2.68,
      "price_change_1h": 12.32,
      "price_change_24h": 737.0,
      "volume_24h": 57611.32,
      "liquidity": 0.0,
      "market_cap": 21940.15,
      "pair_url": "https://dexscreener.com/solana/6ZUS8VVdHTxbfbgxEC2mcdLRxHjx6amLHqh2FkMkpump",
      "token_address": "6ZUS8VVdHTxbfbgxEC2mcdLRxHjx6amLHqh2FkMkpump",
      "chain": "solana",
      "signals": [
        "📈 1h surge: +12.3%",
        "🔥 Daily moon: +737.0% (24h)",
        "🎯 Micro cap gem: $21,940"
      ],
      "timestamp": "2026-03-29T12:45:09.674466"
    },
    {
      "symbol": "FEET",
      "name": "Feet",
      "score": 44,
      "alert_type": "🆕 NEW_PAIR",
      "price": 6.147e-05,
      "price_change_5m": 4.01,
      "price_change_1h": 11.27,
      "price_change_24h": 81.08,
      "volume_24h": 305950.02,
      "liquidity": 19470.28,
      "market_cap": 61473.0,
      "pair_url": "https://dexscreener.com/solana/3dmWv6dKUKxBxrHxDzAsuCXpbRVwVv2ifiXWcSKDpump",
      "token_address": "3dmWv6dKUKxBxrHxDzAsuCXpbRVwVv2ifiXWcSKDpump",
      "chain": "solana",
      "signals": [
        "📈 1h surge: +11.3%",
        "🔥 Daily moon: +81.1% (24h)",
        "🎯 Micro cap gem: $61,473",
        "🔥 Active trading: 9,684 txns (24h)"
      ],
      "timestamp": "2026-03-29T12:45:09.674466"
    },
    {
      "symbol": "LOST",
      "name": "Pumpfun ruined my life",
      "score": 39,
      "alert_type": "🔔 ALERT",
      "price": 0.0006316,
      "price_change_5m": 4.49,
      "price_change_1h": 15.71,
      "price_change_24h": 8.82,
      "volume_24h": 767196.8,
      "liquidity": 73036.03,
      "market_cap": 631586.0,
      "pair_url": "https://dexscreener.com/solana/n3ShrNZRCoMrw5Gww7rPMxVbDq3to3YwsGkDz19pump",
      "token_address": "n3ShrNZRCoMrw5Gww7rPMxVbDq3to3YwsGkDz19pump",
      "chain": "solana",
      "signals": [
        "📈 1h surge: +15.7%",
        "💰 High volume: $767,197",
        "💧 Strong liquidity: $73,036",
        "🎯 Micro cap gem: $631,586",
        "🔥 Active trading: 11,576 txns (24h)"
      ],
      "timestamp": "2026-03-29T12:45:09.674466"
    },
    {
      "symbol": "LEGO",
      "name": "LEGOFICATION",
      "score": 38,
      "alert_type": "🆕 NEW_PAIR",
      "price": 7.109e-05,
      "price_change_5m": 0.07,
      "price_change_1h": 36.08,
      "price_change_24h": 109.0,
      "volume_24h": 202735.42,
      "liquidity": 20657.15,
      "market_cap": 71091.0,
      "pair_url": "https://dexscreener.com/solana/EKGQrjPnQEvtY2nVNCt9x34V6C4GUB9hJTu3BLPpump",
      "token_address": "EKGQrjPnQEvtY2nVNCt9x34V6C4GUB9hJTu3BLPpump",
      "chain": "solana",
      "signals": [
        "📈 1h surge: +36.1%",
        "🔥 Daily moon: +109.0% (24h)",
        "⚡ Heavy buying: 16 buys vs 6 sells (5m)",
        "🎯 Micro cap gem: $71,091",
        "🔥 Active trading: 5,150 txns (24h)"
      ],
      "timestamp": "2026-03-29T12:45:09.674466"
    },
    {
      "symbol": "PUMPPERPS",
      "name": "PumpPerps",
      "score": 36,
      "alert_type": "🆕 NEW_PAIR",
      "price": 0.0003795,
      "price_change_5m": -4.58,
      "price_change_1h": 47.87,
      "price_change_24h": 1016.0,
      "volume_24h": 1119847.97,
      "liquidity": 50354.66,
      "market_cap": 379560.0,
      "pair_url": "https://dexscreener.com/solana/4sgCNP7ykejUaSvaGDhkq7JYqrLKB6M1Gq2X1rxSpump",
      "token_address": "4sgCNP7ykejUaSvaGDhkq7JYqrLKB6M1Gq2X1rxSpump",
      "chain": "solana",
      "signals": [
        "📈 1h surge: +47.9%",
        "🔥 Daily moon: +1016.0% (24h)",
        "💰 High volume: $1,119,848",
        "💧 Strong liquidity: $50,355",
        "🎯 Micro cap gem: $379,560",
        "🔥 Active trading: 24,052 txns (24h)"
      ],
      "timestamp": "2026-03-29T12:45:09.674466"
    },
    {
      "symbol": "TARO",
      "name": "Ryotaro",
      "score": 35,
      "alert_type": "🔔 ALERT",
      "price": 0.0004245,
      "price_change_5m": -0.9,
      "price_change_1h": 22.3,
      "price_change_24h": -25.96,
      "volume_24h": 3723.61,
      "liquidity": 1028.14,
      "market_cap": 424545.0,
      "pair_url": "https://dexscreener.com/solana/6MFiqqkS4MUwmkoa8sj5UJcFzJGVxHD1yEpoyRRUdoge",
      "token_address": "6MFiqqkS4MUwmkoa8sj5UJcFzJGVxHD1yEpoyRRUdoge",
      "chain": "solana",
      "signals": [
        "📈 1h surge: +22.3%",
        "⚡ Heavy buying: 8 buys vs 1 sells (5m)",
        "💪 Buy pressure: 279 buys vs 46 sells (1h)",
        "🎯 Micro cap gem: $424,545",
        "🔥 Active trading: 6,310 txns (24h)"
      ],
      "timestamp": "2026-03-29T12:45:09.674466"
    },
    {
      "symbol": "TARO",
      "name": "Ryotaro",
      "score": 35,
      "alert_type": "🔔 ALERT",
      "price": 0.0,
      "price_change_5m": 0.0,
      "price_change_1h": 13.58,
      "price_change_24h": 16.28,
      "volume_24h": 0.0,
      "liquidity": 0.0,
      "market_cap": 0.0,
      "pair_url": "https://dexscreener.com/solana/6MFiqqkS4MUwmkoa8sj5UJcFzJGVxHD1yEpoyRRUdoge",
      "token_address": "6MFiqqkS4MUwmkoa8sj5UJcFzJGVxHD1yEpoyRRUdoge",
      "chain": "solana",
      "signals": [
        "📈 1h surge: +13.6%",
        "💪 Buy pressure: 2 buys vs 0 sells (1h)",
        "💎 Small cap: $0"
      ],
      "timestamp": "2026-03-29T12:45:09.674466"
    },
    {
      "symbol": "CODEX",
      "name": "CodeX",
      "score": 33,
      "alert_type": "🆕 NEW_PAIR",
      "price": 1.203e-05,
      "price_change_5m": -1.23,
      "price_change_1h": 20.87,
      "price_change_24h": 369.0,
      "volume_24h": 16045.98,
      "liquidity": 0.0,
      "market_cap": 12033.78,
      "pair_url": "https://dexscreener.com/solana/7ZaC375c9Nc57k2Tir9yiHumtinB9MetWDFHPfE2pump",
      "token_address": "7ZaC375c9Nc57k2Tir9yiHumtinB9MetWDFHPfE2pump",
      "chain": "solana",
      "signals": [
        "📈 1h surge: +20.9%",
        "🔥 Daily moon: +369.0% (24h)",
        "⚡ Heavy buying: 35 buys vs 16 sells (5m)",
        "💪 Buy pressure: 193 buys vs 101 sells (1h)",
        "🎯 Micro cap gem: $12,034"
      ],
      "timestamp": "2026-03-29T12:45:09.674466"
    },
    {
      "symbol": "JAKE",
      "name": "Jake The Frog",
      "score": 33,
      "alert_type": "🆕 NEW_PAIR",
      "price": 5.054e-06,
      "price_change_5m": -1.49,
      "price_change_1h": 14.51,
      "price_change_24h": -85.96,
      "volume_24h": 1233327.98,
      "liquidity": 5968.88,
      "market_cap": 5053.0,
      "pair_url": "https://dexscreener.com/solana/7GyghMajWog8Np5fBMiDtFDStntDyCiEZ84nMYiJpump",
      "token_address": "7GyghMajWog8Np5fBMiDtFDStntDyCiEZ84nMYiJpump",
      "chain": "solana",
      "signals": [
        "📈 1h surge: +14.5%",
        "💪 Buy pressure: 9 buys vs 4 sells (1h)",
        "💰 High volume: $1,233,328",
        "🎯 Micro cap gem: $5,053",
        "🔥 Active trading: 21,825 txns (24h)"
      ],
      "timestamp": "2026-03-29T12:45:09.674466"
    },
    {
      "symbol": "DOG",
      "name": "The Crypto Dog",
      "score": 32,
      "alert_type": "💧 LIQUIDITY",
      "price": 0.0005379,
      "price_change_5m": 0.0,
      "price_change_1h": 0.43,
      "price_change_24h": -0.35,
      "volume_24h": 1037.0,
      "liquidity": 134534.48,
      "market_cap": 537960.0,
      "pair_url": "https://dexscreener.com/solana/21CnrFRqvEVkQZUTFmTXjcsJTLZhRY51ohoaCPwRpump",
      "token_address": "21CnrFRqvEVkQZUTFmTXjcsJTLZhRY51ohoaCPwRpump",
      "chain": "solana",
      "signals": [
        "💪 Buy pressure: 1 buys vs 0 sells (1h)",
        "💧 Strong liquidity: $134,534",
        "🎯 Micro cap gem: $537,960"
      ],
      "timestamp": "2026-03-29T12:45:09.674466"
    },
    {
      "symbol": "CAT",
      "name": "Catcoin",
      "score": 32,
      "alert_type": "💧 LIQUIDITY",
      "price": 2.994e-11,
      "price_change_5m": 0.0,
      "price_change_1h": 0.47,
      "price_change_24h": -0.09,
      "volume_24h": 1628.69,
      "liquidity": 144767.6,
      "market_cap": 299383.0,
      "pair_url": "https://dexscreener.com/solana/7hWcHohzwtLddDUG81H2PkWq6KEkMtSDNkYXsso18Fy3",
      "token_address": "7hWcHohzwtLddDUG81H2PkWq6KEkMtSDNkYXsso18Fy3",
      "chain": "solana",
      "signals": [
        "💪 Buy pressure: 4 buys vs 0 sells (1h)",
        "💧 Strong liquidity: $144,768",
        "🎯 Micro cap gem: $299,383"
      ],
      "timestamp": "2026-03-29T12:45:09.674466"
    },
    {
      "symbol": "DOG",
      "name": "Dog (Bitcoin)",
      "score": 29,
      "alert_type": "🔔 ALERT",
      "price": 0.0007415,
      "price_change_5m": 0.0,
      "price_change_1h": -0.29,
      "price_change_24h": -0.54,
      "volume_24h": 36480.39,
      "liquidity": 57717.51,
      "market_cap": 74154986.0,
      "pair_url": "https://dexscreener.com/solana/dog1viwbb2vWDpER5FrJ4YFG6gq6XuyFohUe9TXN65u",
      "token_address": "dog1viwbb2vWDpER5FrJ4YFG6gq6XuyFohUe9TXN65u",
      "chain": "solana",
      "signals": [
        "💪 Buy pressure: 14 buys vs 2 sells (1h)",
        "💧 Strong liquidity: $57,718"
      ],
      "timestamp": "2026-03-29T12:45:09.674466"
    },
    {
      "symbol": "TARO",
      "name": "Ryotaro",
      "score": 28,
      "alert_type": "🔔 ALERT",
      "price": 0.0004219,
      "price_change_5m": 0.86,
      "price_change_1h": 18.39,
      "price_change_24h": -24.93,
      "volume_24h": 499.93,
      "liquidity": 59.92,
      "market_cap": 421971.0,
      "pair_url": "https://dexscreener.com/solana/6MFiqqkS4MUwmkoa8sj5UJcFzJGVxHD1yEpoyRRUdoge",
      "token_address": "6MFiqqkS4MUwmkoa8sj5UJcFzJGVxHD1yEpoyRRUdoge",
      "chain": "solana",
      "signals": [
        "📈 1h surge: +18.4%",
        "🎯 Micro cap gem: $421,971",
        "🔥 Active trading: 44,552 txns (24h)"
      ],
      "timestamp": "2026-03-29T12:45:09.674466"
    },
    {
      "symbol": "BANANA",
      "name": "BA NANA",
      "score": 26,
      "alert_type": "🆕 NEW_PAIR",
      "price": 3.052e-06,
      "price_change_5m": -1.49,
      "price_change_1h": 24.73,
      "price_change_24h": -91.49,
      "volume_24h": 730244.41,
      "liquidity": 4469.91,
      "market_cap": 3053.0,
      "pair_url": "https://dexscreener.com/solana/7iunYwDWdbSRQehho26GXGP7tjFbArMrHQqdkBgmpump",
      "token_address": "7iunYwDWdbSRQehho26GXGP7tjFbArMrHQqdkBgmpump",
      "chain": "solana",
      "signals": [
        "📈 1h surge: +24.7%",
        "💰 High volume: $730,244",
        "🎯 Micro cap gem: $3,053",
        "🔥 Active trading: 25,158 txns (24h)"
      ],
      "timestamp": "2026-03-29T12:45:09.674466"
    },
    {
      "symbol": "AI",
      "name": "trash can",
      "score": 22,
      "alert_type": "🆕 NEW_PAIR",
      "price": 0.0004251,
      "price_change_5m": 0.0,
      "price_change_1h": 0.0,
      "price_change_24h": -0.02,
      "volume_24h": 1052.5,
      "liquidity": 17005249.94,
      "market_cap": 425131243.0,
      "pair_url": "https://dexscreener.com/solana/2q9d43ZL6X33PJDjm7pU7W6JL9gK3V8adAQBb8niPnM2",
      "token_address": "2q9d43ZL6X33PJDjm7pU7W6JL9gK3V8adAQBb8niPnM2",
      "chain": "solana",
      "signals": [
        "💧 Strong liquidity: $17,005,250"
      ],
      "timestamp": "2026-03-29T12:45:09.674466"
    },
    {
      "symbol": "TARO",
      "name": "Ryotaro",
      "score": 21,
      "alert_type": "🔔 ALERT",
      "price": 0.0003981,
      "price_change_5m": -5.7,
      "price_change_1h": 12.36,
      "price_change_24h": -29.6,
      "volume_24h": 280677.46,
      "liquidity": 49967.41,
      "market_cap": 398172.0,
      "pair_url": "https://dexscreener.com/solana/6MFiqqkS4MUwmkoa8sj5UJcFzJGVxHD1yEpoyRRUdoge",
      "token_address": "6MFiqqkS4MUwmkoa8sj5UJcFzJGVxHD1yEpoyRRUdoge",
      "chain": "solana",
      "signals": [
        "📈 1h surge: +12.4%",
        "🎯 Micro cap gem: $398,172",
        "🔥 Active trading: 11,659 txns (24h)"
      ],
      "timestamp": "2026-03-29T12:45:09.674466"
    },
    {
      "symbol": "SWING",
      "name": "The Last Swing",
      "score": 20,
      "alert_type": "🔔 ALERT",
      "price": 8.593e-05,
      "price_change_5m": -5.28,
      "price_change_1h": 9.13,
      "price_change_24h": -22.75,
      "volume_24h": 279500.36,
      "liquidity": 26009.37,
      "market_cap": 85933.0,
      "pair_url": "https://dexscreener.com/solana/2izfNJ5bACaQDKyqGUYicSKhFE963TnkBo9tWxiqpump",
      "token_address": "2izfNJ5bACaQDKyqGUYicSKhFE963TnkBo9tWxiqpump",
      "chain": "solana",
      "signals": [
        "🎯 Micro cap gem: $85,933",
        "🔥 Active trading: 9,795 txns (24h)"
      ],
      "timestamp": "2026-03-29T12:45:09.674466"
    },
    {
      "symbol": "AI",
      "name": "chain GENSYNAI_COIN COIn",
      "score": 20,
      "alert_type": "🔔 ALERT",
      "price": 0.0001379,
      "price_change_5m": 0.02,
      "price_change_1h": -0.06,
      "price_change_24h": 71.38,
      "volume_24h": 26772789.3,
      "liquidity": 82793.17,
      "market_cap": 137949.0,
      "pair_url": "https://dexscreener.com/solana/FVXXkrJnrB9Cd9HD4MmPxJpMraAY3BRk57Enz329FBS1",
      "token_address": "FVXXkrJnrB9Cd9HD4MmPxJpMraAY3BRk57Enz329FBS1",
      "chain": "solana",
      "signals": [
        "🔥 Daily moon: +71.4% (24h)",
        "💰 High volume: $26,772,789",
        "💧 Strong liquidity: $82,793",
        "🎯 Micro cap gem: $137,949",
        "🔥 Active trading: 102,821 txns (24h)"
      ],
      "timestamp": "2026-03-29T12:45:09.674466"
    }
  ],
  "lastUpdated": "2026-03-29T12:45:09.674466",
  "totalScanned": 149,
  "generatedAt": "12:45"
}